{
  "logo": "/images/logo.png",
  "image_alt": "Logo",
  "background": "#6C5CE7",
  "nav": [
    {
      "link": "/",
      "text": "Home"
    },
    {
      "link": "/about",
      "text": "About Us"
    },
    {
      "link": "/service",
      "text": "Service"
    },
    {
      "link": "/gallery",
      "text": "Gallery"
    },
    {
      "link": "voucher",
      "text": "Gift card/ vouchers"
    },
    {
      "link": "booking",
      "text": "Booking"
    },
    {
      "link": "contact",
      "text": "Contact Us"
    }   
  ],
  "_inputs": {
    "logo": {
      "type": "image"
    },
    "background": {
      "type": "color"
    }
  }
}
